description_harvester/__init__.py
description_harvester/configurator.py
description_harvester/iiif_utils.py
description_harvester/plugins.py
description_harvester/utils.py
description_harvester/version.py
description_harvester/inputs/aspace.py
description_harvester/inputs/ead.py
description_harvester/models/arclight.py
description_harvester/models/description.py
description_harvester/models/model_utils.py
description_harvester/outputs/arclight.py
description_harvester/plugins/default.py
description_harvester-0.9.2.dist-info/licenses/LICENSE
tests/conftest.py
tests/test_arclight.py
tests/test_aspace.py
tests/test_aspace_advanced.py
tests/test_ead.py
tests/test_ead_chronlist.py
tests/test_iiif_utils.py
description_harvester-0.9.2.dist-info/METADATA
description_harvester-0.9.2.dist-info/WHEEL
description_harvester-0.9.2.dist-info/entry_points.txt
description_harvester-0.9.2.dist-info/top_level.txt
description_harvester-0.9.2.dist-info/RECORD
