Metadata-Version: 2.4
Name: description_harvester
Version: 0.9.2
Summary: A tool for working with archival description for public access.
Home-page: https://github.com/UAlbanyArchives/description_harvester
Author: Gregory Wiedeman
Author-email: gwiedeman@albany.edu
Classifier: Programming Language :: Python :: 3
Classifier: License :: OSI Approved :: MIT License
Classifier: Operating System :: OS Independent
Requires-Python: >=3.9
License-File: LICENSE
Requires-Dist: archivessnake<1,>=0.9.1
Requires-Dist: beautifulsoup4>=4.12.0
Requires-Dist: black>=22.1.0
Requires-Dist: langcodes<4,==3.5.0
Requires-Dist: lxml>=5.0.0
Requires-Dist: pysolr<4,>=3.9.0
Requires-Dist: pyyaml<7,>=6.0
Requires-Dist: jsonmodels
Requires-Dist: requests<3,>=2.28.1
Dynamic: author
Dynamic: author-email
Dynamic: classifier
Dynamic: description
Dynamic: description-content-type
Dynamic: home-page
Dynamic: license-file
Dynamic: requires-dist
Dynamic: requires-python
Dynamic: summary
